stackedwaterfalls/__init__.py
stackedwaterfalls/stackedwaterfalls.py
stackedwaterfalls-0.3.0.dist-info/LICENSE
stackedwaterfalls-0.3.0.dist-info/METADATA
stackedwaterfalls-0.3.0.dist-info/WHEEL
stackedwaterfalls-0.3.0.dist-info/top_level.txt
stackedwaterfalls-0.3.0.dist-info/RECORD
