Metadata-Version: 2.1
Name: stackedwaterfalls
Version: 0.3.0
Summary: A small utility to create stacked waterfalls using matplotlib
Home-page: https://github.com/askprash/stackedwaterfall
Author: Prashanth
Author-email: prash@mit.edu
License: UNKNOWN
Project-URL: Bug Tracker, https://github.com/askprash/stackedwaterfall/issues
Platform: UNKNOWN
Classifier: Programming Language :: Python :: 3
Classifier: License :: OSI Approved :: MIT License
Classifier: Operating System :: OS Independent
Requires-Python: >=3.6
License-File: LICENSE
